dbt_duckdb_udf/__init__.py
dbt_duckdb_udf/plugin.py
dbt_duckdb_udf/udf/__init__.py
dbt_duckdb_udf/udf/sample/string_udf.py
dbt_duckdb_udf/utils/utils.py
dbt_duckdb_udf-0.0.4.dist-info/METADATA
dbt_duckdb_udf-0.0.4.dist-info/WHEEL
dbt_duckdb_udf-0.0.4.dist-info/licenses/LICENSE
dbt_duckdb_udf-0.0.4.dist-info/RECORD
